mokafaa_client/__init__.py
mokafaa_client/client.py
mokafaa_client-0.1.0.dist-info/METADATA
mokafaa_client-0.1.0.dist-info/WHEEL
mokafaa_client-0.1.0.dist-info/top_level.txt
mokafaa_client-0.1.0.dist-info/RECORD
