Metadata-Version: 2.1
Name: mokafaa-client
Version: 0.1.0
Summary: A Python client for the Mokafaa loyalty API
Home-page: https://github.com/ahmad18189/mokafaa-client
Author: Ahmed Abdelrahman
Author-email: ahmad18189@gmail.com
Project-URL: Source, https://github.com/ahmad18189/mokafaa-client
Project-URL: Tracker, https://github.com/ahmad18189/mokafaa-client/issues
Keywords: API client Mokafaa loyalty
Classifier: Development Status :: 4 - Beta
Classifier: Intended Audience :: Developers
Classifier: License :: OSI Approved :: MIT License
Classifier: Programming Language :: Python :: 3
Classifier: Programming Language :: Python :: 3.6
Classifier: Programming Language :: Python :: 3.7
Classifier: Programming Language :: Python :: 3.8
Classifier: Programming Language :: Python :: 3.9
Classifier: Programming Language :: Python :: 3.10
Requires-Python: >=3.6
Requires-Dist: requests
